efficient_test/__init__.py
efficient_test/chinacitycode.py
efficient_test/chinesecardbin.py
efficient_test/chinesename.py
efficient_test/core.py
efficient_test/dbhelper.py
efficient_test/jmeter.py
efficient_test/sh_and_os_ext.py
efficient_test-1.0.5.dist-info/LICENSE
efficient_test-1.0.5.dist-info/METADATA
efficient_test-1.0.5.dist-info/WHEEL
efficient_test-1.0.5.dist-info/top_level.txt
efficient_test-1.0.5.dist-info/RECORD
