Metadata-Version: 2.1
Name: efficient-test
Version: 1.0.5
Summary: testdata include chinese personal four element and offen use datetime 测试数据包含随机生成的中国公民四要素，及常用的日期时间｜通过身份证号获得性别、生日、年龄，识别真伪｜根据swagger文档生成规则用例
Home-page: http://www.cnblogs.com/yicaifeitian/
Author: YuWeiPeng
Author-email: 404051211@qq.com
License: UNKNOWN
Platform: UNKNOWN
Classifier: Programming Language :: Python :: 3
Classifier: License :: OSI Approved :: MIT License
Classifier: Operating System :: OS Independent
Requires-Python: >=3.6
License-File: LICENSE
Requires-Dist: requests (>=2.24.0)
Requires-Dist: python-dateutil (>=2.8.1)
Requires-Dist: SQLAlchemy (>=1.3.17)
Requires-Dist: records (>=0.5.3)
